<?xml version="1.0" encoding="UTF-8"?>
<con:soapui-project id="67a51407-ad2a-45e0-8f9d-f0d58ccde93f" activeEnvironment="Default" name="public-lighting" resourceRoot="" soapui-version="5.2.1" xmlns:con="http://eviware.com/soapui/config"><con:settings/><con:interface xsi:type="con:WsdlInterface" id="1082bd9f-306e-4ff2-bb11-05983db6879d" wsaVersion="NONE" name="PublicLightingAdHocManagementPortSoap11" type="wsdl" bindingName="{http://www.alliander.com/definitions/osgp/publiclighting/adhocmanagement-v1.0}PublicLightingAdHocManagementPortSoap11" soapVersion="1_1" anonymous="optional" definition="https://localhost/osgp-adapter-ws-publiclighting/wsdl/PublicLighting/PublicLightingAdHocManagement.wsdl" xmlns:xsi="http://www.w3.org/2001/XMLSchema-instance"><con:settings/><con:definitionCache type="TEXT" rootPart="https://localhost/osgp-adapter-ws-publiclighting/wsdl/PublicLighting/PublicLightingAdHocManagement.wsdl"><con:part><con:url>https://localhost/osgp-adapter-ws-publiclighting/wsdl/PublicLighting/PublicLightingAdHocManagement.wsdl</con:url><con:content><![CDATA[<!--Platform version: 4.0.0-SNAPSHOT -->
<wsdl:definitions targetNamespace="http://www.alliander.com/definitions/osgp/publiclighting/adhocmanagement-v1.0" xmlns:wsdl="http://schemas.xmlsoap.org/wsdl/" xmlns:ahman="http://www.alliander.com/schemas/osgp/publiclighting/adhocmanagement/2014/10" xmlns:common="http://www.alliander.com/schemas/osgp/common/2014/10" xmlns:soap="http://schemas.xmlsoap.org/wsdl/soap/" xmlns:tns="http://www.alliander.com/definitions/osgp/publiclighting/adhocmanagement-v1.0">
  <wsdl:types>
    <xsd:schema targetNamespace="http://www.alliander.com/definitions/osgp/publiclighting/adhocmanagement/imports" xmlns:xsd="http://www.w3.org/2001/XMLSchema">
      <xsd:import namespace="http://www.alliander.com/schemas/osgp/publiclighting/adhocmanagement/2014/10" schemaLocation="schemas/pl-adhocmanagement.xsd"/>
    </xsd:schema>
  </wsdl:types>
  <wsdl:message name="FindAllDevicesHeader">
    <wsdl:part element="common:OrganisationIdentification" name="OrganisationIdentification"/>
    <wsdl:part element="common:UserName" name="UserName"/>
    <wsdl:part element="common:ApplicationName" name="ApplicationName"/>
  </wsdl:message>
  <wsdl:message name="FindAllDevicesRequest">
    <wsdl:part element="ahman:FindAllDevicesRequest" name="FindAllDevicesRequest"></wsdl:part>
  </wsdl:message>
  <wsdl:message name="FindAllDevicesResponse">
    <wsdl:part element="ahman:FindAllDevicesResponse" name="FindAllDevicesResponse"></wsdl:part>
  </wsdl:message>
  <wsdl:message name="SetLightHeader">
    <wsdl:part element="common:OrganisationIdentification" name="OrganisationIdentification"/>
    <wsdl:part element="common:UserName" name="UserName"/>
    <wsdl:part element="common:ApplicationName" name="ApplicationName"/>
  </wsdl:message>
  <wsdl:message name="SetLightRequest">
    <wsdl:part element="ahman:SetLightRequest" name="SetLightRequest"></wsdl:part>
  </wsdl:message>
  <wsdl:message name="SetLightAsyncResponse">
    <wsdl:part element="ahman:SetLightAsyncResponse" name="SetLightAsyncResponse"></wsdl:part>
  </wsdl:message>
  <wsdl:message name="SetLightAsyncHeader">
    <wsdl:part element="common:OrganisationIdentification" name="OrganisationIdentification"/>
    <wsdl:part element="common:UserName" name="UserName"/>
    <wsdl:part element="common:ApplicationName" name="ApplicationName"/>
  </wsdl:message>
  <wsdl:message name="SetLightAsyncRequest">
    <wsdl:part element="ahman:SetLightAsyncRequest" name="SetLightAsyncRequest"></wsdl:part>
  </wsdl:message>
  <wsdl:message name="SetLightResponse">
    <wsdl:part element="ahman:SetLightResponse" name="SetLightResponse"></wsdl:part>
  </wsdl:message>
  <wsdl:message name="GetStatusHeader">
    <wsdl:part element="common:OrganisationIdentification" name="OrganisationIdentification"/>
    <wsdl:part element="common:UserName" name="UserName"/>
    <wsdl:part element="common:ApplicationName" name="ApplicationName"/>
  </wsdl:message>
  <wsdl:message name="GetStatusRequest">
    <wsdl:part element="ahman:GetStatusRequest" name="GetStatusRequest"></wsdl:part>
  </wsdl:message>
  <wsdl:message name="GetStatusAsyncResponse">
    <wsdl:part element="ahman:GetStatusAsyncResponse" name="GetStatusAsyncResponse"></wsdl:part>
  </wsdl:message>
  <wsdl:message name="GetStatusAsyncHeader">
    <wsdl:part element="common:OrganisationIdentification" name="OrganisationIdentification"/>
    <wsdl:part element="common:UserName" name="UserName"/>
    <wsdl:part element="common:ApplicationName" name="ApplicationName"/>
  </wsdl:message>
  <wsdl:message name="GetStatusAsyncRequest">
    <wsdl:part element="ahman:GetStatusAsyncRequest" name="GetStatusAsyncRequest"></wsdl:part>
  </wsdl:message>
  <wsdl:message name="GetStatusResponse">
    <wsdl:part element="ahman:GetStatusResponse" name="GetStatusResponse"></wsdl:part>
  </wsdl:message>
  <wsdl:message name="ResumeScheduleHeader">
    <wsdl:part element="common:OrganisationIdentification" name="OrganisationIdentification"/>
    <wsdl:part element="common:UserName" name="UserName"/>
    <wsdl:part element="common:ApplicationName" name="ApplicationName"/>
  </wsdl:message>
  <wsdl:message name="ResumeScheduleRequest">
    <wsdl:part element="ahman:ResumeScheduleRequest" name="ResumeScheduleRequest"></wsdl:part>
  </wsdl:message>
  <wsdl:message name="ResumeScheduleAsyncResponse">
    <wsdl:part element="ahman:ResumeScheduleAsyncResponse" name="ResumeScheduleAsyncResponse"></wsdl:part>
  </wsdl:message>
  <wsdl:message name="ResumeScheduleAsyncHeader">
    <wsdl:part element="common:OrganisationIdentification" name="OrganisationIdentification"/>
    <wsdl:part element="common:UserName" name="UserName"/>
    <wsdl:part element="common:ApplicationName" name="ApplicationName"/>
  </wsdl:message>
  <wsdl:message name="ResumeScheduleAsyncRequest">
    <wsdl:part element="ahman:ResumeScheduleAsyncRequest" name="ResumeScheduleAsyncRequest"></wsdl:part>
  </wsdl:message>
  <wsdl:message name="ResumeScheduleResponse">
    <wsdl:part element="ahman:ResumeScheduleResponse" name="ResumeScheduleResponse"></wsdl:part>
  </wsdl:message>
  <wsdl:message name="SetTransitionHeader">
    <wsdl:part element="common:OrganisationIdentification" name="OrganisationIdentification"/>
    <wsdl:part element="common:UserName" name="UserName"/>
    <wsdl:part element="common:ApplicationName" name="ApplicationName"/>
  </wsdl:message>
  <wsdl:message name="SetTransitionRequest">
    <wsdl:part element="ahman:SetTransitionRequest" name="SetTransitionRequest"></wsdl:part>
  </wsdl:message>
  <wsdl:message name="SetTransitionAsyncResponse">
    <wsdl:part element="ahman:SetTransitionAsyncResponse" name="SetTransitionAsyncResponse"></wsdl:part>
  </wsdl:message>
  <wsdl:message name="SetTransitionAsyncHeader">
    <wsdl:part element="common:OrganisationIdentification" name="OrganisationIdentification"/>
    <wsdl:part element="common:UserName" name="UserName"/>
    <wsdl:part element="common:ApplicationName" name="ApplicationName"/>
  </wsdl:message>
  <wsdl:message name="SetTransitionAsyncRequest">
    <wsdl:part element="ahman:SetTransitionAsyncRequest" name="SetTransitionAsyncRequest"></wsdl:part>
  </wsdl:message>
  <wsdl:message name="SetTransitionResponse">
    <wsdl:part element="ahman:SetTransitionResponse" name="SetTransitionResponse"></wsdl:part>
  </wsdl:message>
  <wsdl:portType name="PublicLightingAdHocManagementPort">
    <wsdl:operation name="FindAllDevices">
      <wsdl:input message="tns:FindAllDevicesRequest" name="FindAllDevicesRequest"></wsdl:input>
      <wsdl:output message="tns:FindAllDevicesResponse" name="FindAllDevicesResponse"></wsdl:output>
    </wsdl:operation>
    <wsdl:operation name="SetLight">
      <wsdl:input message="tns:SetLightRequest" name="SetLightRequest"></wsdl:input>
      <wsdl:output message="tns:SetLightAsyncResponse" name="SetLightAsyncResponse"></wsdl:output>
    </wsdl:operation>
    <wsdl:operation name="GetSetLightResponse">
      <wsdl:input message="tns:SetLightAsyncRequest" name="SetLightAsyncRequest"></wsdl:input>
      <wsdl:output message="tns:SetLightResponse" name="SetLightResponse"></wsdl:output>
    </wsdl:operation>
    <wsdl:operation name="GetStatus">
      <wsdl:input message="tns:GetStatusRequest" name="GetStatusRequest"></wsdl:input>
      <wsdl:output message="tns:GetStatusAsyncResponse" name="GetStatusAsyncResponse"></wsdl:output>
    </wsdl:operation>
    <wsdl:operation name="GetGetStatusResponse">
      <wsdl:input message="tns:GetStatusAsyncRequest" name="GetStatusAsyncRequest"></wsdl:input>
      <wsdl:output message="tns:GetStatusResponse" name="GetStatusResponse"></wsdl:output>
    </wsdl:operation>
    <wsdl:operation name="ResumeSchedule">
      <wsdl:input message="tns:ResumeScheduleRequest" name="ResumeScheduleRequest"></wsdl:input>
      <wsdl:output message="tns:ResumeScheduleAsyncResponse" name="ResumeScheduleAsyncResponse"></wsdl:output>
    </wsdl:operation>
    <wsdl:operation name="GetResumeScheduleResponse">
      <wsdl:input message="tns:ResumeScheduleAsyncRequest" name="ResumeScheduleAsyncRequest"></wsdl:input>
      <wsdl:output message="tns:ResumeScheduleResponse" name="ResumeScheduleResponse"></wsdl:output>
    </wsdl:operation>
    <wsdl:operation name="SetTransition">
      <wsdl:input message="tns:SetTransitionRequest" name="SetTransitionRequest"></wsdl:input>
      <wsdl:output message="tns:SetTransitionAsyncResponse" name="SetTransitionAsyncResponse"></wsdl:output>
    </wsdl:operation>
    <wsdl:operation name="GetSetTransitionResponse">
      <wsdl:input message="tns:SetTransitionAsyncRequest" name="SetTransitionAsyncRequest"></wsdl:input>
      <wsdl:output message="tns:SetTransitionResponse" name="SetTransitionResponse"></wsdl:output>
    </wsdl:operation>
  </wsdl:portType>
  <wsdl:binding name="PublicLightingAdHocManagementPortSoap11" type="tns:PublicLightingAdHocManagementPort">
    <soap:binding style="document" transport="http://schemas.xmlsoap.org/soap/http"/>
    <wsdl:operation name="FindAllDevices">
      <soap:operation soapAction=""/>
      <wsdl:input name="FindAllDevicesRequest">
        <soap:header message="tns:FindAllDevicesHeader" part="OrganisationIdentification" use="literal"/>
        <soap:header message="tns:FindAllDevicesHeader" part="UserName" use="literal"/>
        <soap:header message="tns:FindAllDevicesHeader" part="ApplicationName" use="literal"/>
        <soap:body use="literal"/>
      </wsdl:input>
      <wsdl:output name="FindAllDevicesResponse">
        <soap:body use="literal"/>
      </wsdl:output>
    </wsdl:operation>
    <wsdl:operation name="SetLight">
      <soap:operation soapAction=""/>
      <wsdl:input name="SetLightRequest">
        <soap:header message="tns:SetLightHeader" part="OrganisationIdentification" use="literal"/>
        <soap:header message="tns:SetLightHeader" part="UserName" use="literal"/>
        <soap:header message="tns:SetLightHeader" part="ApplicationName" use="literal"/>
        <soap:body use="literal"/>
      </wsdl:input>
      <wsdl:output name="SetLightAsyncResponse">
        <soap:body use="literal"/>
      </wsdl:output>
    </wsdl:operation>
    <wsdl:operation name="GetSetLightResponse">
      <soap:operation soapAction=""/>
      <wsdl:input name="SetLightAsyncRequest">
        <soap:header message="tns:SetLightAsyncHeader" part="OrganisationIdentification" use="literal"/>
        <soap:header message="tns:SetLightAsyncHeader" part="UserName" use="literal"/>
        <soap:header message="tns:SetLightAsyncHeader" part="ApplicationName" use="literal"/>
        <soap:body use="literal"/>
      </wsdl:input>
      <wsdl:output name="SetLightResponse">
        <soap:body use="literal"/>
      </wsdl:output>
    </wsdl:operation>
    <wsdl:operation name="GetStatus">
      <soap:operation soapAction=""/>
      <wsdl:input name="GetStatusRequest">
        <soap:header message="tns:GetStatusHeader" part="OrganisationIdentification" use="literal"/>
        <soap:header message="tns:GetStatusHeader" part="UserName" use="literal"/>
        <soap:header message="tns:GetStatusHeader" part="ApplicationName" use="literal"/>
        <soap:body use="literal"/>
      </wsdl:input>
      <wsdl:output name="GetStatusAsyncResponse">
        <soap:body use="literal"/>
      </wsdl:output>
    </wsdl:operation>
    <wsdl:operation name="GetGetStatusResponse">
      <soap:operation soapAction=""/>
      <wsdl:input name="GetStatusAsyncRequest">
        <soap:header message="tns:GetStatusAsyncHeader" part="OrganisationIdentification" use="literal"/>
        <soap:header message="tns:GetStatusAsyncHeader" part="UserName" use="literal"/>
        <soap:header message="tns:GetStatusAsyncHeader" part="ApplicationName" use="literal"/>
        <soap:body use="literal"/>
      </wsdl:input>
      <wsdl:output name="GetStatusResponse">
        <soap:body use="literal"/>
      </wsdl:output>
    </wsdl:operation>
    <wsdl:operation name="ResumeSchedule">
      <soap:operation soapAction=""/>
      <wsdl:input name="ResumeScheduleRequest">
        <soap:header message="tns:ResumeScheduleHeader" part="OrganisationIdentification" use="literal"/>
        <soap:header message="tns:ResumeScheduleHeader" part="UserName" use="literal"/>
        <soap:header message="tns:ResumeScheduleHeader" part="ApplicationName" use="literal"/>
        <soap:body use="literal"/>
      </wsdl:input>
      <wsdl:output name="ResumeScheduleAsyncResponse">
        <soap:body use="literal"/>
      </wsdl:output>
    </wsdl:operation>
    <wsdl:operation name="GetResumeScheduleResponse">
      <soap:operation soapAction=""/>
      <wsdl:input name="ResumeScheduleAsyncRequest">
        <soap:header message="tns:ResumeScheduleAsyncHeader" part="OrganisationIdentification" use="literal"/>
        <soap:header message="tns:ResumeScheduleAsyncHeader" part="UserName" use="literal"/>
        <soap:header message="tns:ResumeScheduleAsyncHeader" part="ApplicationName" use="literal"/>
        <soap:body use="literal"/>
      </wsdl:input>
      <wsdl:output name="ResumeScheduleResponse">
        <soap:body use="literal"/>
      </wsdl:output>
    </wsdl:operation>
    <wsdl:operation name="SetTransition">
      <soap:operation soapAction=""/>
      <wsdl:input name="SetTransitionRequest">
        <soap:header message="tns:SetTransitionHeader" part="OrganisationIdentification" use="literal"/>
        <soap:header message="tns:SetTransitionHeader" part="UserName" use="literal"/>
        <soap:header message="tns:SetTransitionHeader" part="ApplicationName" use="literal"/>
        <soap:body use="literal"/>
      </wsdl:input>
      <wsdl:output name="SetTransitionAsyncResponse">
        <soap:body use="literal"/>
      </wsdl:output>
    </wsdl:operation>
    <wsdl:operation name="GetSetTransitionResponse">
      <soap:operation soapAction=""/>
      <wsdl:input name="SetTransitionAsyncRequest">
        <soap:header message="tns:SetTransitionAsyncHeader" part="OrganisationIdentification" use="literal"/>
        <soap:header message="tns:SetTransitionAsyncHeader" part="UserName" use="literal"/>
        <soap:header message="tns:SetTransitionAsyncHeader" part="ApplicationName" use="literal"/>
        <soap:body use="literal"/>
      </wsdl:input>
      <wsdl:output name="SetTransitionResponse">
        <soap:body use="literal"/>
      </wsdl:output>
    </wsdl:operation>
  </wsdl:binding>
  <wsdl:service name="PublicLightingAdHocManagementPortService">
    <wsdl:port binding="tns:PublicLightingAdHocManagementPortSoap11" name="PublicLightingAdHocManagementPortSoap11">
      <soap:address location="https://localhost:443/osgp-adapter-ws-publiclighting/publiclighting/adHocManagementService/"/>
    </wsdl:port>
  </wsdl:service>
</wsdl:definitions>]]></con:content><con:type>http://schemas.xmlsoap.org/wsdl/</con:type></con:part><con:part><con:url>https://localhost/osgp-adapter-ws-publiclighting/wsdl/PublicLighting/schemas/pl-adhocmanagement.xsd</con:url><con:content><![CDATA[<xsd:schema attributeFormDefault="unqualified" elementFormDefault="qualified" targetNamespace="http://www.alliander.com/schemas/osgp/publiclighting/adhocmanagement/2014/10" xmlns:xsd="http://www.w3.org/2001/XMLSchema" xmlns:common="http://www.alliander.com/schemas/osgp/common/2014/10" xmlns:tns="http://www.alliander.com/schemas/osgp/publiclighting/adhocmanagement/2014/10">
  <xsd:import namespace="http://www.alliander.com/schemas/osgp/common/2014/10" schemaLocation="common.xsd"/>
  <xsd:element name="FindAllDevicesRequest">
    <xsd:complexType>
      <xsd:sequence>
        <xsd:element name="Page" type="xsd:int"/>
      </xsd:sequence>
    </xsd:complexType>
  </xsd:element>
  <xsd:element name="FindAllDevicesResponse">
    <xsd:complexType>
      <xsd:sequence>
        <xsd:element name="DevicePage" type="tns:DevicePage"/>
      </xsd:sequence>
    </xsd:complexType>
  </xsd:element>
  <xsd:element name="SetLightRequest">
    <xsd:complexType>
      <xsd:sequence>
        <xsd:element minOccurs="1" name="DeviceIdentification" type="common:Identification"/>
        <xsd:element maxOccurs="6" name="LightValue" type="tns:LightValue"/>
      </xsd:sequence>
    </xsd:complexType>
  </xsd:element>
  <xsd:element name="SetLightAsyncResponse">
    <xsd:complexType>
      <xsd:sequence>
        <xsd:element name="AsyncResponse" type="common:AsyncResponse"/>
      </xsd:sequence>
    </xsd:complexType>
  </xsd:element>
  <xsd:element name="SetLightAsyncRequest">
    <xsd:complexType>
      <xsd:sequence>
        <xsd:element name="AsyncRequest" type="common:AsyncRequest"/>
      </xsd:sequence>
    </xsd:complexType>
  </xsd:element>
  <xsd:element name="SetLightResponse">
    <xsd:complexType>
      <xsd:sequence>
        <xsd:element minOccurs="1" name="Result" type="common:OsgpResultType"/>
        <xsd:element name="Description" type="xsd:string"/>
      </xsd:sequence>
    </xsd:complexType>
  </xsd:element>
  <xsd:element name="GetStatusRequest">
    <xsd:complexType>
      <xsd:sequence>
        <xsd:element minOccurs="1" name="DeviceIdentification" type="common:Identification"/>
      </xsd:sequence>
    </xsd:complexType>
  </xsd:element>
  <xsd:element name="GetStatusAsyncResponse">
    <xsd:complexType>
      <xsd:sequence>
        <xsd:element name="AsyncResponse" type="common:AsyncResponse"/>
      </xsd:sequence>
    </xsd:complexType>
  </xsd:element>
  <xsd:element name="GetStatusAsyncRequest">
    <xsd:complexType>
      <xsd:sequence>
        <xsd:element name="AsyncRequest" type="common:AsyncRequest"/>
      </xsd:sequence>
    </xsd:complexType>
  </xsd:element>
  <xsd:element name="GetStatusResponse">
    <xsd:complexType>
      <xsd:sequence>
        <xsd:element minOccurs="1" name="Result" type="common:OsgpResultType"/>
        <xsd:element name="Description" type="xsd:string"/>
        <xsd:element name="DeviceStatus" type="tns:DeviceStatus"/>
      </xsd:sequence>
    </xsd:complexType>
  </xsd:element>
  <xsd:element name="ResumeScheduleRequest">
    <xsd:complexType>
      <xsd:sequence>
        <xsd:element minOccurs="1" name="DeviceIdentification" type="common:Identification"/>
        <xsd:element minOccurs="0" name="Index">
          <xsd:simpleType>
            <xsd:restriction base="xsd:int">
              <xsd:minInclusive value="0"/>
              <xsd:maxInclusive value="6"/>
            </xsd:restriction>
          </xsd:simpleType>
        </xsd:element>
        <xsd:element name="IsImmediate" type="xsd:boolean"/>
      </xsd:sequence>
    </xsd:complexType>
  </xsd:element>
  <xsd:element name="ResumeScheduleAsyncResponse">
    <xsd:complexType>
      <xsd:sequence>
        <xsd:element name="AsyncResponse" type="common:AsyncResponse"/>
      </xsd:sequence>
    </xsd:complexType>
  </xsd:element>
  <xsd:element name="ResumeScheduleAsyncRequest">
    <xsd:complexType>
      <xsd:sequence>
        <xsd:element name="AsyncRequest" type="common:AsyncRequest"/>
      </xsd:sequence>
    </xsd:complexType>
  </xsd:element>
  <xsd:element name="ResumeScheduleResponse">
    <xsd:complexType>
      <xsd:sequence>
        <xsd:element minOccurs="1" name="Result" type="common:OsgpResultType"/>
        <xsd:element name="Description" type="xsd:string"/>
      </xsd:sequence>
    </xsd:complexType>
  </xsd:element>
  <xsd:element name="SetTransitionRequest">
    <xsd:complexType>
      <xsd:sequence>
        <xsd:element minOccurs="1" name="DeviceIdentification" type="common:Identification"/>
        <xsd:element minOccurs="1" name="TransitionType" type="tns:TransitionType"/>
        <xsd:element minOccurs="0" name="Time" type="xsd:time"/>
      </xsd:sequence>
    </xsd:complexType>
  </xsd:element>
  <xsd:element name="SetTransitionAsyncResponse">
    <xsd:complexType>
      <xsd:sequence>
        <xsd:element name="AsyncResponse" type="common:AsyncResponse"/>
      </xsd:sequence>
    </xsd:complexType>
  </xsd:element>
  <xsd:element name="SetTransitionAsyncRequest">
    <xsd:complexType>
      <xsd:sequence>
        <xsd:element name="AsyncRequest" type="common:AsyncRequest"/>
      </xsd:sequence>
    </xsd:complexType>
  </xsd:element>
  <xsd:element name="SetTransitionResponse">
    <xsd:complexType>
      <xsd:sequence>
        <xsd:element minOccurs="1" name="Result" type="common:OsgpResultType"/>
        <xsd:element name="Description" type="xsd:string"/>
      </xsd:sequence>
    </xsd:complexType>
  </xsd:element>
  <xsd:complexType name="DeviceStatus">
    <xsd:sequence>
      <xsd:element maxOccurs="unbounded" name="LightValues" type="tns:LightValue"/>
      <xsd:element maxOccurs="1" minOccurs="1" name="PreferredLinkType" type="tns:LinkType"/>
      <xsd:element maxOccurs="1" minOccurs="1" name="ActualLinkType" type="tns:LinkType"/>
      <xsd:element maxOccurs="1" minOccurs="0" name="LightType" type="tns:LightType"/>
      <xsd:element maxOccurs="8" minOccurs="0" name="EventNotifications" type="tns:EventNotificationType"/>
    </xsd:sequence>
  </xsd:complexType>
  <xsd:complexType name="Device">
    <xsd:sequence>
      <xsd:element name="DeviceUid" type="xsd:string"/>
      <xsd:element name="DeviceIdentification" type="common:Identification"/>
      <xsd:element minOccurs="0" name="ContainerPostalCode" type="xsd:string"/>
      <xsd:element minOccurs="0" name="ContainerCity" type="xsd:string"/>
      <xsd:element minOccurs="0" name="ContainerStreet" type="xsd:string"/>
      <xsd:element minOccurs="0" name="ContainerNumber" type="xsd:string"/>
      <xsd:element minOccurs="0" name="GpsLatitude" type="xsd:float"/>
      <xsd:element minOccurs="0" name="GpsLongitude" type="xsd:float"/>
      <xsd:element name="DeviceType" type="xsd:string"/>
      <xsd:element name="Activated" type="xsd:boolean"/>
      <xsd:element name="HasSchedule" type="xsd:boolean"/>
      <xsd:element name="PublicKeyPresent" type="xsd:boolean"/>
    </xsd:sequence>
  </xsd:complexType>
  <xsd:complexType name="DevicePage">
    <xsd:sequence>
      <xsd:element name="TotalPages" type="xsd:int"/>
      <xsd:element maxOccurs="unbounded" name="Devices" type="tns:Device"/>
    </xsd:sequence>
  </xsd:complexType>
  <xsd:complexType name="LightValue">
    <xsd:sequence>
      <xsd:element minOccurs="0" name="Index">
        <xsd:simpleType>
          <xsd:restriction base="xsd:int">
            <xsd:minInclusive value="0"/>
            <xsd:maxInclusive value="6"/>
          </xsd:restriction>
        </xsd:simpleType>
      </xsd:element>
      <xsd:element name="On" type="xsd:boolean"/>
      <xsd:element minOccurs="0" name="DimValue">
        <xsd:simpleType>
          <xsd:restriction base="xsd:int">
            <xsd:minInclusive value="1"/>
            <xsd:maxInclusive value="100"/>
          </xsd:restriction>
        </xsd:simpleType>
      </xsd:element>
    </xsd:sequence>
  </xsd:complexType>
  <xsd:simpleType name="LightType">
    <xsd:restriction base="xsd:string">
      <xsd:enumeration value="LT_NOT_SET"/>
      <xsd:enumeration value="RELAY"/>
      <xsd:enumeration value="ONE_TO_TEN_VOLT"/>
      <xsd:enumeration value="ONE_TO_TEN_VOLT_REVERSE"/>
      <xsd:enumeration value="DALI"/>
    </xsd:restriction>
  </xsd:simpleType>
  <xsd:simpleType name="LinkType">
    <xsd:restriction base="xsd:string">
      <xsd:enumeration value="LINK_NOT_SET"/>
      <xsd:enumeration value="GPRS"/>
      <xsd:enumeration value="CDMA"/>
      <xsd:enumeration value="ETHERNET"/>
    </xsd:restriction>
  </xsd:simpleType>
  <xsd:simpleType name="EventNotificationType">
    <xsd:restriction base="xsd:string">
      <xsd:enumeration value="DIAG_EVENTS"/>
      <xsd:enumeration value="HARDWARE_FAILURE"/>
      <xsd:enumeration value="LIGHT_EVENTS"/>
      <xsd:enumeration value="TARIFF_EVENTS"/>
      <xsd:enumeration value="MONITOR_EVENTS"/>
      <xsd:enumeration value="FIRMWARE_EVENTS"/>
      <xsd:enumeration value="COMM_EVENTS"/>
      <xsd:enumeration value="SECURITY_EVENTS"/>
    </xsd:restriction>
  </xsd:simpleType>
  <xsd:simpleType name="TransitionType">
    <xsd:restriction base="xsd:string">
      <xsd:enumeration value="NIGHT_DAY"/>
      <xsd:enumeration value="DAY_NIGHT"/>
    </xsd:restriction>
  </xsd:simpleType>
</xsd:schema>]]></con:content><con:type>http://www.w3.org/2001/XMLSchema</con:type></con:part><con:part><con:url>https://localhost/osgp-adapter-ws-publiclighting/wsdl/PublicLighting/schemas/common.xsd</con:url><con:content><![CDATA[<xsd:schema attributeFormDefault="unqualified" elementFormDefault="qualified" targetNamespace="http://www.alliander.com/schemas/osgp/common/2014/10" xmlns:xsd="http://www.w3.org/2001/XMLSchema" xmlns:tns="http://www.alliander.com/schemas/osgp/common/2014/10">
  <xsd:element name="OrganisationIdentification" type="tns:Identification"/>
  <xsd:element name="UserName" type="tns:Identification"/>
  <xsd:element name="ApplicationName" type="tns:Identification"/>
  <xsd:simpleType name="Identification">
    <xsd:restriction base="xsd:normalizedString">
      <xsd:minLength value="1"/>
      <xsd:maxLength value="40"/>
      <xsd:pattern value="[^ ]{0,40}"/>
    </xsd:restriction>
  </xsd:simpleType>
  <xsd:complexType name="Page">
    <xsd:sequence>
      <xsd:element maxOccurs="1" minOccurs="1" name="TotalPages" type="xsd:int"/>
      <xsd:element maxOccurs="1" minOccurs="1" name="PageSize" type="xsd:int"/>
      <xsd:element maxOccurs="1" minOccurs="1" name="CurrentPage" type="xsd:int"/>
    </xsd:sequence>
  </xsd:complexType>
  <xsd:simpleType name="CorrelationUid">
    <xsd:restriction base="xsd:normalizedString">
      <xsd:minLength value="20"/>
    </xsd:restriction>
  </xsd:simpleType>
  <xsd:complexType name="AsyncRequest">
    <xsd:sequence>
      <xsd:element minOccurs="1" name="CorrelationUid" type="tns:CorrelationUid"/>
      <xsd:element minOccurs="1" name="DeviceId" type="tns:Identification"/>
    </xsd:sequence>
  </xsd:complexType>
  <xsd:complexType name="AsyncResponse">
    <xsd:sequence>
      <xsd:element minOccurs="1" name="CorrelationUid" type="tns:CorrelationUid"/>
      <xsd:element minOccurs="1" name="DeviceId" type="tns:Identification"/>
    </xsd:sequence>
  </xsd:complexType>
  <xsd:simpleType name="OsgpResultType">
    <xsd:restriction base="xsd:string">
      <xsd:enumeration value="OK"/>
      <xsd:enumeration value="NOT FOUND"/>
      <xsd:enumeration value="NOT OK"/>
    </xsd:restriction>
  </xsd:simpleType>
  <xsd:element name="FunctionalFault">
    <xsd:complexType>
      <xsd:sequence>
        <xsd:element maxOccurs="1" minOccurs="1" name="Code" type="xsd:int"/>
        <xsd:element maxOccurs="1" minOccurs="1" name="Message" type="xsd:string"/>
        <xsd:element maxOccurs="1" minOccurs="1" name="Component" type="xsd:string"/>
        <xsd:element maxOccurs="1" minOccurs="1" name="InnerException" type="xsd:string"/>
        <xsd:element maxOccurs="1" minOccurs="1" name="InnerMessage" type="xsd:string"/>
      </xsd:sequence>
    </xsd:complexType>
  </xsd:element>
  <xsd:element name="TechnicalFault">
    <xsd:complexType>
      <xsd:sequence>
        <xsd:element maxOccurs="1" minOccurs="1" name="Message" type="xsd:string"/>
        <xsd:element maxOccurs="1" minOccurs="1" name="Component" type="xsd:string"/>
        <xsd:element maxOccurs="1" minOccurs="1" name="InnerException" type="xsd:string"/>
        <xsd:element maxOccurs="1" minOccurs="1" name="InnerMessage" type="xsd:string"/>
      </xsd:sequence>
    </xsd:complexType>
  </xsd:element>
</xsd:schema>]]></con:content><con:type>http://www.w3.org/2001/XMLSchema</con:type></con:part></con:definitionCache><con:endpoints><con:endpoint>https://localhost:443/osgp-adapter-ws-publiclighting/publiclighting/adHocManagementService/</con:endpoint></con:endpoints><con:operation id="c8761300-c088-42b9-8383-4e78b9a558d3" isOneWay="false" action="" name="FindAllDevices" bindingOperationName="FindAllDevices" type="Request-Response" outputName="FindAllDevicesResponse" inputName="FindAllDevicesRequest" receivesAttachments="false" sendsAttachments="false" anonymous="optional"><con:settings/><con:call id="400dbd07-f9db-4f94-bfd0-eb8df7a79bf7" name="Request 1"><con:settings/><con:encoding>UTF-8</con:encoding><con:endpoint>https://localhost:443/osgp-adapter-ws-publiclighting/publiclighting/adHocManagementService/</con:endpoint><con:request><![CDATA[<soapenv:Envelope xmlns:soapenv="http://schemas.xmlsoap.org/soap/envelope/" xmlns:ns="http://www.alliander.com/schemas/osgp/common/2014/10" xmlns:ns1="http://www.alliander.com/schemas/osgp/publiclighting/adhocmanagement/2014/10">
   <soapenv:Header>
      <ns:ApplicationName>quae divum incedo</ns:ApplicationName>
      <ns:UserName>sonoras imperio</ns:UserName>
      <ns:OrganisationIdentification>gero et</ns:OrganisationIdentification>
   </soapenv:Header>
   <soapenv:Body>
      <ns1:FindAllDevicesRequest>
         <!--type: int-->
         <ns1:Page>3</ns1:Page>
      </ns1:FindAllDevicesRequest>
   </soapenv:Body>
</soapenv:Envelope>]]></con:request><con:wsaConfig mustUnderstand="NONE" version="200508" action="http://www.alliander.com/definitions/osgp/publiclighting/adhocmanagement-v1.0/PublicLightingAdHocManagementPort/FindAllDevicesRequest"/></con:call></con:operation><con:operation id="d61c70b1-87c7-4619-a6b6-1df6b058dc45" isOneWay="false" action="" name="GetGetStatusResponse" bindingOperationName="GetGetStatusResponse" type="Request-Response" outputName="GetStatusResponse" inputName="GetStatusAsyncRequest" receivesAttachments="false" sendsAttachments="false" anonymous="optional"><con:settings/><con:call id="9a894bdc-a1d0-43e9-bdcf-91ec1665a255" name="Request 1"><con:settings/><con:encoding>UTF-8</con:encoding><con:endpoint>https://localhost:443/osgp-adapter-ws-publiclighting/publiclighting/adHocManagementService/</con:endpoint><con:request><![CDATA[<soapenv:Envelope xmlns:soapenv="http://schemas.xmlsoap.org/soap/envelope/" xmlns:ns="http://www.alliander.com/schemas/osgp/common/2014/10" xmlns:ns1="http://www.alliander.com/schemas/osgp/publiclighting/adhocmanagement/2014/10">
   <soapenv:Header>
      <ns:ApplicationName>per auras</ns:ApplicationName>
      <ns:UserName>verrantque per auras</ns:UserName>
      <ns:OrganisationIdentification>quae divum incedo</ns:OrganisationIdentification>
   </soapenv:Header>
   <soapenv:Body>
      <ns1:GetStatusAsyncRequest>
         <ns1:AsyncRequest>
            <!--type: CorrelationUid-->
            <ns:CorrelationUid>gero etgero etgero etgero et</ns:CorrelationUid>
            <!--type: Identification-->
            <ns:DeviceId>sonoras imperio</ns:DeviceId>
         </ns1:AsyncRequest>
      </ns1:GetStatusAsyncRequest>
   </soapenv:Body>
</soapenv:Envelope>]]></con:request><con:wsaConfig mustUnderstand="NONE" version="200508" action="http://www.alliander.com/definitions/osgp/publiclighting/adhocmanagement-v1.0/PublicLightingAdHocManagementPort/GetStatusAsyncRequest"/></con:call></con:operation><con:operation id="03ce20c0-a9e9-4fdf-bc9c-327de8dddff5" isOneWay="false" action="" name="GetResumeScheduleResponse" bindingOperationName="GetResumeScheduleResponse" type="Request-Response" outputName="ResumeScheduleResponse" inputName="ResumeScheduleAsyncRequest" receivesAttachments="false" sendsAttachments="false" anonymous="optional"><con:settings/><con:call id="26c0a61f-3d3f-417e-bab2-633831f92bc6" name="Request 1"><con:settings/><con:encoding>UTF-8</con:encoding><con:endpoint>https://localhost:443/osgp-adapter-ws-publiclighting/publiclighting/adHocManagementService/</con:endpoint><con:request><![CDATA[<soapenv:Envelope xmlns:soapenv="http://schemas.xmlsoap.org/soap/envelope/" xmlns:ns="http://www.alliander.com/schemas/osgp/common/2014/10" xmlns:ns1="http://www.alliander.com/schemas/osgp/publiclighting/adhocmanagement/2014/10">
   <soapenv:Header>
      <ns:ApplicationName>per auras</ns:ApplicationName>
      <ns:UserName>verrantque per auras</ns:UserName>
      <ns:OrganisationIdentification>quae divum incedo</ns:OrganisationIdentification>
   </soapenv:Header>
   <soapenv:Body>
      <ns1:ResumeScheduleAsyncRequest>
         <ns1:AsyncRequest>
            <!--type: CorrelationUid-->
            <ns:CorrelationUid>gero etgero etgero etgero et</ns:CorrelationUid>
            <!--type: Identification-->
            <ns:DeviceId>sonoras imperio</ns:DeviceId>
         </ns1:AsyncRequest>
      </ns1:ResumeScheduleAsyncRequest>
   </soapenv:Body>
</soapenv:Envelope>]]></con:request><con:wsaConfig mustUnderstand="NONE" version="200508" action="http://www.alliander.com/definitions/osgp/publiclighting/adhocmanagement-v1.0/PublicLightingAdHocManagementPort/ResumeScheduleAsyncRequest"/></con:call></con:operation><con:operation id="0ae1363e-927e-4b99-8309-dde55e0bf1f5" isOneWay="false" action="" name="GetSetLightResponse" bindingOperationName="GetSetLightResponse" type="Request-Response" outputName="SetLightResponse" inputName="SetLightAsyncRequest" receivesAttachments="false" sendsAttachments="false" anonymous="optional"><con:settings/><con:call id="852a258a-770f-4169-9455-e668904e3e71" name="Request 1"><con:settings/><con:encoding>UTF-8</con:encoding><con:endpoint>https://localhost:443/osgp-adapter-ws-publiclighting/publiclighting/adHocManagementService/</con:endpoint><con:request><![CDATA[<soapenv:Envelope xmlns:soapenv="http://schemas.xmlsoap.org/soap/envelope/" xmlns:ns="http://www.alliander.com/schemas/osgp/common/2014/10" xmlns:ns1="http://www.alliander.com/schemas/osgp/publiclighting/adhocmanagement/2014/10">
   <soapenv:Header>
      <ns:ApplicationName>per auras</ns:ApplicationName>
      <ns:UserName>verrantque per auras</ns:UserName>
      <ns:OrganisationIdentification>quae divum incedo</ns:OrganisationIdentification>
   </soapenv:Header>
   <soapenv:Body>
      <ns1:SetLightAsyncRequest>
         <ns1:AsyncRequest>
            <!--type: CorrelationUid-->
            <ns:CorrelationUid>gero etgero etgero etgero et</ns:CorrelationUid>
            <!--type: Identification-->
            <ns:DeviceId>sonoras imperio</ns:DeviceId>
         </ns1:AsyncRequest>
      </ns1:SetLightAsyncRequest>
   </soapenv:Body>
</soapenv:Envelope>]]></con:request><con:wsaConfig mustUnderstand="NONE" version="200508" action="http://www.alliander.com/definitions/osgp/publiclighting/adhocmanagement-v1.0/PublicLightingAdHocManagementPort/SetLightAsyncRequest"/></con:call></con:operation><con:operation id="889d4a7e-05ca-4bb3-a97a-f6d9f1c4a020" isOneWay="false" action="" name="GetSetTransitionResponse" bindingOperationName="GetSetTransitionResponse" type="Request-Response" outputName="SetTransitionResponse" inputName="SetTransitionAsyncRequest" receivesAttachments="false" sendsAttachments="false" anonymous="optional"><con:settings/><con:call id="3222f792-1b67-4619-abb8-1ef1c6390f25" name="Request 1"><con:settings/><con:encoding>UTF-8</con:encoding><con:endpoint>https://localhost:443/osgp-adapter-ws-publiclighting/publiclighting/adHocManagementService/</con:endpoint><con:request><![CDATA[<soapenv:Envelope xmlns:soapenv="http://schemas.xmlsoap.org/soap/envelope/" xmlns:ns="http://www.alliander.com/schemas/osgp/common/2014/10" xmlns:ns1="http://www.alliander.com/schemas/osgp/publiclighting/adhocmanagement/2014/10">
   <soapenv:Header>
      <ns:ApplicationName>per auras</ns:ApplicationName>
      <ns:UserName>verrantque per auras</ns:UserName>
      <ns:OrganisationIdentification>quae divum incedo</ns:OrganisationIdentification>
   </soapenv:Header>
   <soapenv:Body>
      <ns1:SetTransitionAsyncRequest>
         <ns1:AsyncRequest>
            <!--type: CorrelationUid-->
            <ns:CorrelationUid>gero etgero etgero etgero et</ns:CorrelationUid>
            <!--type: Identification-->
            <ns:DeviceId>sonoras imperio</ns:DeviceId>
         </ns1:AsyncRequest>
      </ns1:SetTransitionAsyncRequest>
   </soapenv:Body>
</soapenv:Envelope>]]></con:request><con:wsaConfig mustUnderstand="NONE" version="200508" action="http://www.alliander.com/definitions/osgp/publiclighting/adhocmanagement-v1.0/PublicLightingAdHocManagementPort/SetTransitionAsyncRequest"/></con:call></con:operation><con:operation id="b67d2fe9-9484-412c-a422-5e1292e7e451" isOneWay="false" action="" name="GetStatus" bindingOperationName="GetStatus" type="Request-Response" outputName="GetStatusAsyncResponse" inputName="GetStatusRequest" receivesAttachments="false" sendsAttachments="false" anonymous="optional"><con:settings/><con:call id="0858bc62-f4f4-49e8-b923-d71ec5167026" name="Request 1"><con:settings/><con:encoding>UTF-8</con:encoding><con:endpoint>https://localhost:443/osgp-adapter-ws-publiclighting/publiclighting/adHocManagementService/</con:endpoint><con:request><![CDATA[<soapenv:Envelope xmlns:soapenv="http://schemas.xmlsoap.org/soap/envelope/" xmlns:ns="http://www.alliander.com/schemas/osgp/common/2014/10" xmlns:ns1="http://www.alliander.com/schemas/osgp/publiclighting/adhocmanagement/2014/10">
   <soapenv:Header>
      <ns:ApplicationName>verrantque per auras</ns:ApplicationName>
      <ns:UserName>quae divum incedo</ns:UserName>
      <ns:OrganisationIdentification>sonoras imperio</ns:OrganisationIdentification>
   </soapenv:Header>
   <soapenv:Body>
      <ns1:GetStatusRequest>
         <!--type: Identification-->
         <ns1:DeviceIdentification>gero et</ns1:DeviceIdentification>
      </ns1:GetStatusRequest>
   </soapenv:Body>
</soapenv:Envelope>]]></con:request><con:wsaConfig mustUnderstand="NONE" version="200508" action="http://www.alliander.com/definitions/osgp/publiclighting/adhocmanagement-v1.0/PublicLightingAdHocManagementPort/GetStatusRequest"/></con:call></con:operation><con:operation id="f9233d9e-92e8-4723-883e-ad4e21c512da" isOneWay="false" action="" name="ResumeSchedule" bindingOperationName="ResumeSchedule" type="Request-Response" outputName="ResumeScheduleAsyncResponse" inputName="ResumeScheduleRequest" receivesAttachments="false" sendsAttachments="false" anonymous="optional"><con:settings/><con:call id="87d0e033-a4e2-4760-8ed0-bb5dc8c85bf2" name="Request 1"><con:settings/><con:encoding>UTF-8</con:encoding><con:endpoint>https://localhost:443/osgp-adapter-ws-publiclighting/publiclighting/adHocManagementService/</con:endpoint><con:request><![CDATA[<soapenv:Envelope xmlns:soapenv="http://schemas.xmlsoap.org/soap/envelope/" xmlns:ns="http://www.alliander.com/schemas/osgp/common/2014/10" xmlns:ns1="http://www.alliander.com/schemas/osgp/publiclighting/adhocmanagement/2014/10">
   <soapenv:Header>
      <ns:ApplicationName>temperat iras</ns:ApplicationName>
      <ns:UserName>ventos tempestatesque</ns:UserName>
      <ns:OrganisationIdentification>aeoliam venit</ns:OrganisationIdentification>
   </soapenv:Header>
   <soapenv:Body>
      <ns1:ResumeScheduleRequest>
         <!--type: Identification-->
         <ns1:DeviceIdentification>gero et</ns1:DeviceIdentification>
         <!--Optional:-->
         <!--anonymous type-->
         <ns1:Index>3</ns1:Index>
         <!--type: boolean-->
         <ns1:IsImmediate>true</ns1:IsImmediate>
      </ns1:ResumeScheduleRequest>
   </soapenv:Body>
</soapenv:Envelope>]]></con:request><con:wsaConfig mustUnderstand="NONE" version="200508" action="http://www.alliander.com/definitions/osgp/publiclighting/adhocmanagement-v1.0/PublicLightingAdHocManagementPort/ResumeScheduleRequest"/></con:call></con:operation><con:operation id="be53f336-8422-4b5d-864d-dfd7c1950771" isOneWay="false" action="" name="SetLight" bindingOperationName="SetLight" type="Request-Response" outputName="SetLightAsyncResponse" inputName="SetLightRequest" receivesAttachments="false" sendsAttachments="false" anonymous="optional"><con:settings/><con:call id="bf1a998d-5ebc-4645-984c-defc964a36de" name="Request 1"><con:settings/><con:encoding>UTF-8</con:encoding><con:endpoint>https://localhost:443/osgp-adapter-ws-publiclighting/publiclighting/adHocManagementService/</con:endpoint><con:request><![CDATA[<soapenv:Envelope xmlns:soapenv="http://schemas.xmlsoap.org/soap/envelope/" xmlns:ns="http://www.alliander.com/schemas/osgp/common/2014/10" xmlns:ns1="http://www.alliander.com/schemas/osgp/publiclighting/adhocmanagement/2014/10">
   <soapenv:Header>
      <ns:ApplicationName>temperat iras</ns:ApplicationName>
      <ns:UserName>ventos tempestatesque</ns:UserName>
      <ns:OrganisationIdentification>aeoliam venit</ns:OrganisationIdentification>
   </soapenv:Header>
   <soapenv:Body>
      <ns1:SetLightRequest>
         <!--type: Identification-->
         <ns1:DeviceIdentification>gero et</ns1:DeviceIdentification>
         <!--1 to 6 repetitions:-->
         <ns1:LightValue>
            <!--Optional:-->
            <!--anonymous type-->
            <ns1:Index>3</ns1:Index>
            <!--type: boolean-->
            <ns1:On>true</ns1:On>
            <!--Optional:-->
            <!--anonymous type-->
            <ns1:DimValue>3</ns1:DimValue>
         </ns1:LightValue>
      </ns1:SetLightRequest>
   </soapenv:Body>
</soapenv:Envelope>]]></con:request><con:wsaConfig mustUnderstand="NONE" version="200508" action="http://www.alliander.com/definitions/osgp/publiclighting/adhocmanagement-v1.0/PublicLightingAdHocManagementPort/SetLightRequest"/></con:call></con:operation><con:operation id="2ecf11fb-3403-4859-8630-fe9592a4f95e" isOneWay="false" action="" name="SetTransition" bindingOperationName="SetTransition" type="Request-Response" outputName="SetTransitionAsyncResponse" inputName="SetTransitionRequest" receivesAttachments="false" sendsAttachments="false" anonymous="optional"><con:settings/><con:call id="6fb41785-cb38-4a6f-b166-99824939a4aa" name="Request 1"><con:settings/><con:encoding>UTF-8</con:encoding><con:endpoint>https://localhost:443/osgp-adapter-ws-publiclighting/publiclighting/adHocManagementService/</con:endpoint><con:request><![CDATA[<soapenv:Envelope xmlns:soapenv="http://schemas.xmlsoap.org/soap/envelope/" xmlns:ns="http://www.alliander.com/schemas/osgp/common/2014/10" xmlns:ns1="http://www.alliander.com/schemas/osgp/publiclighting/adhocmanagement/2014/10">
   <soapenv:Header>
      <ns:ApplicationName>circum claustra</ns:ApplicationName>
      <ns:UserName>per auras</ns:UserName>
      <ns:OrganisationIdentification>verrantque per auras</ns:OrganisationIdentification>
   </soapenv:Header>
   <soapenv:Body>
      <ns1:SetTransitionRequest>
         <!--type: Identification-->
         <ns1:DeviceIdentification>gero et</ns1:DeviceIdentification>
         <!--type: TransitionType - enumeration: [NIGHT_DAY,DAY_NIGHT]-->
         <ns1:TransitionType>NIGHT_DAY</ns1:TransitionType>
         <!--Optional:-->
         <!--type: time-->
         <ns1:Time>23:18:33</ns1:Time>
      </ns1:SetTransitionRequest>
   </soapenv:Body>
</soapenv:Envelope>]]></con:request><con:wsaConfig mustUnderstand="NONE" version="200508" action="http://www.alliander.com/definitions/osgp/publiclighting/adhocmanagement-v1.0/PublicLightingAdHocManagementPort/SetTransitionRequest"/></con:call></con:operation></con:interface><con:properties/><con:wssContainer><con:crypto><con:source>/home/dev/Sources/Config/certificates/osgp-ca/certs/test-org.pfx</con:source><con:password>1234</con:password><con:type>KEYSTORE</con:type></con:crypto></con:wssContainer><con:oAuth2ProfileContainer/><con:sensitiveInformation/></con:soapui-project>